django_polls/__init__.py
django_polls/admin.py
django_polls/apps.py
django_polls/models.py
django_polls/tests.py
django_polls/urls.py
django_polls/views.py
django_polls/migrations/0001_initial.py
django_polls/migrations/__init__.py
django_polls/static/polls/style.css
django_polls/static/polls/images/background.jpg
django_polls/templates/polls/detail.html
django_polls/templates/polls/index.html
django_polls/templates/polls/results.html
django_polls52-0.1.dist-info/licenses/LICENSE
django_polls52-0.1.dist-info/METADATA
django_polls52-0.1.dist-info/WHEEL
django_polls52-0.1.dist-info/top_level.txt
django_polls52-0.1.dist-info/RECORD
